verinfast/__init__.py
verinfast/agent.py
verinfast/config.yaml
verinfast/reset.sh
verinfast/cloud/aws/blocks.py
verinfast/cloud/aws/costs.py
verinfast/cloud/aws/instances.py
verinfast/cloud/aws/regions.py
verinfast/cloud/azure/blocks.py
verinfast/cloud/azure/costs.py
verinfast/cloud/azure/instances.py
verinfast/cloud/gcp/blocks.py
verinfast/cloud/gcp/instances.py
verinfast/cloud/gcp/zones.py
verinfast/dependencies/walk.py
verinfast/dependencies/walkers/README.md
verinfast/dependencies/walkers/classes.py
verinfast/dependencies/walkers/maven.py
verinfast/dependencies/walkers/npm.py
verinfast/dependencies/walkers/nuget.py
verinfast/dependencies/walkers/python.py
verinfast/utils/utils.py
verinfast-2023.8.15184132.dist-info/METADATA
verinfast-2023.8.15184132.dist-info/WHEEL
verinfast-2023.8.15184132.dist-info/entry_points.txt
verinfast-2023.8.15184132.dist-info/licenses/LICENSE
verinfast-2023.8.15184132.dist-info/RECORD
