Metadata-Version: 2.1
Name: verinfast
Version: 2023.8.15184132
Summary: This tool safely and securely analyzes applications for benchmarking.
Project-URL: Homepage, https://github.com/StartupOS/verinfast
Project-URL: Bug Tracker, https://github.com/StartupOS/verinfast/issues
Project-URL: Source, https://github.com/StartupOS/verinfast
Author-email: Jason Nichols <github@startupos.dev>, Sean Conrad <github@startupos.dev>
License-File: LICENSE
Classifier: License :: Free for non-commercial use
Classifier: Operating System :: OS Independent
Classifier: Programming Language :: Python :: 3
Requires-Python: >=3.10
Requires-Dist: azure-identity
Requires-Dist: azure-mgmt-compute
Requires-Dist: azure-mgmt-monitor
Requires-Dist: azure-mgmt-network
Requires-Dist: azure-mgmt-resource
Requires-Dist: azure-mgmt-storage
Requires-Dist: azure-monitor-query
Requires-Dist: boto3
Requires-Dist: coverage>=7.2.7
Requires-Dist: defusedxml
Requires-Dist: flake8
Requires-Dist: flake8-pytest-style
Requires-Dist: google-cloud-compute>=1.14.0
Requires-Dist: google-cloud-monitoring>=2.15.1
Requires-Dist: google-cloud-storage>=2.10.0
Requires-Dist: httpx[http2]
Requires-Dist: johnnydep
Requires-Dist: modernmetric>=1.0.2
Requires-Dist: pandas
Requires-Dist: protobuf
Requires-Dist: pygount==1.6.1
Requires-Dist: pytest
Requires-Dist: pytest-cov
Requires-Dist: pyyaml
Requires-Dist: semgrep
